aws_common_modules/__init__.py
aws_common_modules/route53.py
aws_common_modules-0.11.dist-info/METADATA
aws_common_modules-0.11.dist-info/WHEEL
aws_common_modules-0.11.dist-info/licenses/LICENSE
aws_common_modules-0.11.dist-info/RECORD
